pydgraph/__init__.py
pydgraph/client.py
pydgraph/client_stub.py
pydgraph/convert.py
pydgraph/errors.py
pydgraph/meta.py
pydgraph/txn.py
pydgraph/util.py
pydgraph/proto/__init__.py
pydgraph/proto/api_pb2.py
pydgraph/proto/api_pb2_grpc.py
joshua_test1-23.0.2.dist-info/LICENSE
joshua_test1-23.0.2.dist-info/METADATA
joshua_test1-23.0.2.dist-info/WHEEL
joshua_test1-23.0.2.dist-info/top_level.txt
joshua_test1-23.0.2.dist-info/RECORD
