Metadata-Version: 2.1
Name: joshua-test1
Version: 23.0.2
Summary: Official Dgraph client implementation for Python
Author-email: Dgraph Labs <contact@dgraph.io>
License: Apache License
Project-URL: Homepage, https://github.com/dgraph-io/pydgraph
Classifier: Intended Audience :: Developers
Classifier: License :: OSI Approved :: Apache Software License
Classifier: Operating System :: OS Independent
Classifier: Topic :: Database
Classifier: Topic :: Software Development
Classifier: Programming Language :: Python :: 3.11
Requires-Python: >=3.7
License-File: LICENSE
Requires-Dist: grpcio (==1.54.0)
Requires-Dist: protobuf (==4.22.3)
Provides-Extra: dev
Requires-Dist: build (==0.10.0) ; extra == 'dev'
Requires-Dist: grpcio-tools (==1.54.0) ; extra == 'dev'
Requires-Dist: pytest (==7.3.1) ; extra == 'dev'
